pymarks/__about__.py
pymarks/__init__.py
pymarks/__main__.py
pymarks/actions.py
pymarks/backup.py
pymarks/bookmark.py
pymarks/constants.py
pymarks/database.py
pymarks/display.py
pymarks/files.py
pymarks/info.py
pymarks/keys.py
pymarks/logger.py
pymarks/scrape.py
pymarks/utils.py
pymarks-0.0.13.dist-info/METADATA
pymarks-0.0.13.dist-info/WHEEL
pymarks-0.0.13.dist-info/entry_points.txt
pymarks-0.0.13.dist-info/licenses/LICENSE.txt
pymarks-0.0.13.dist-info/RECORD
