Metadata-Version: 2.1
Name: pymarks
Version: 0.0.13
Summary: Simple tool to manage your bookmarks
Project-URL: Documentation, https://github.com/haaag/PyMarks#readme
Project-URL: Issues, https://github.com/haaag/PyMarks/issues
Project-URL: Source, https://github.com/haaag/PyMarks/
Author-email: haaag <git.haaag@gmail.com>
License: MIT License
License-File: LICENSE.txt
Classifier: Development Status :: 4 - Beta
Classifier: Programming Language :: Python
Classifier: Programming Language :: Python :: 3.7
Classifier: Programming Language :: Python :: 3.8
Classifier: Programming Language :: Python :: 3.9
Classifier: Programming Language :: Python :: 3.10
Classifier: Programming Language :: Python :: 3.11
Classifier: Programming Language :: Python :: Implementation :: CPython
Classifier: Programming Language :: Python :: Implementation :: PyPy
Requires-Python: >=3.7
Requires-Dist: beautifulsoup4>=4.4.1
Requires-Dist: html5lib
Requires-Dist: httpx
Requires-Dist: pyselector>=0.0.23
